<?xml version="1.0" encoding="UTF-8"?>
<GenRun Id="impl_1" LaunchPart="xc7a100tcsg324-1" LaunchTime="1666318790">
  <File Type="ROUTE-PWR" Name="multi_8y_power_routed.rpt"/>
  <File Type="PA-TCL" Name="multi_8y.tcl"/>
  <File Type="ROUTE-PWR-SUM" Name="multi_8y_power_summary_routed.pb"/>
  <File Type="REPORTS-TCL" Name="multi_8y_reports.tcl"/>
  <File Type="BITSTR-MSK" Name="multi_8y.msk"/>
  <File Type="ROUTE-CLK" Name="multi_8y_clock_utilization_routed.rpt"/>
  <File Type="RDI-RDI" Name="multi_8y.vdi"/>
  <File Type="BG-BIT" Name="multi_8y.bit"/>
  <File Type="BG-DRC" Name="multi_8y.drc"/>
  <File Type="BG-BGN" Name="multi_8y.bgn"/>
  <File Type="BG-BIN" Name="multi_8y.bin"/>
  <File Type="BITSTR-RBT" Name="multi_8y.rbt"/>
  <File Type="BITSTR-NKY" Name="multi_8y.nky"/>
  <File Type="BITSTR-BMM" Name="multi_8y_bd.bmm"/>
  <File Type="ROUTE-METHODOLOGY-DRC" Name="multi_8y_methodology_drc_routed.rpt"/>
  <File Type="BITSTR-MMI" Name="multi_8y.mmi"/>
  <File Type="BITSTR-SYSDEF" Name="multi_8y.sysdef"/>
  <File Type="BITSTR-LTX" Name="debug_nets.ltx"/>
  <File Type="BITSTR-LTX" Name="multi_8y.ltx"/>
  <File Type="WBT-USG" Name="usage_statistics_webtalk.html"/>
  <File Type="OPT-DRC" Name="multi_8y_drc_opted.rpt"/>
  <File Type="OPT-HWDEF" Name="multi_8y.hwdef"/>
  <File Type="PLACE-IO" Name="multi_8y_io_placed.rpt"/>
  <File Type="PLACE-UTIL" Name="multi_8y_utilization_placed.rpt"/>
  <File Type="PLACE-UTIL-PB" Name="multi_8y_utilization_placed.pb"/>
  <File Type="PLACE-CTRL" Name="multi_8y_control_sets_placed.rpt"/>
  <File Type="PLACE-PRE-SIMILARITY" Name="multi_8y_incremental_reuse_pre_placed.rpt"/>
  <File Type="ROUTE-DRC" Name="multi_8y_drc_routed.rpt"/>
  <File Type="ROUTE-DRC-PB" Name="multi_8y_drc_routed.pb"/>
  <File Type="ROUTE-PWR-RPX" Name="multi_8y_power_routed.rpx"/>
  <File Type="ROUTE-STATUS" Name="multi_8y_route_status.rpt"/>
  <File Type="ROUTE-STATUS-PB" Name="multi_8y_route_status.pb"/>
  <File Type="ROUTE-DCP" Name="multi_8y_routed.dcp"/>
  <File Type="ROUTE-ERROR-DCP" Name="multi_8y_routed_error.dcp"/>
  <File Type="ROUTE-BLACKBOX-DCP" Name="multi_8y_routed_bb.dcp"/>
  <File Type="ROUTE-TIMINGSUMMARY" Name="multi_8y_timing_summary_routed.rpt"/>
  <File Type="ROUTE-TIMING-PB" Name="multi_8y_timing_summary_routed.pb"/>
  <File Type="ROUTE-TIMING-RPX" Name="multi_8y_timing_summary_routed.rpx"/>
  <File Type="ROUTE-BUS-SKEW" Name="multi_8y_bus_skew_routed.rpt"/>
  <File Type="ROUTE-BUS-SKEW-PB" Name="multi_8y_bus_skew_routed.pb"/>
  <File Type="ROUTE-BUS-SKEW-RPX" Name="multi_8y_bus_skew_routed.rpx"/>
  <File Type="OPT-DCP" Name="multi_8y_opt.dcp"/>
  <File Type="PLACE-DCP" Name="multi_8y_placed.dcp"/>
  <File Type="PWROPT-DCP" Name="multi_8y_pwropt.dcp"/>
  <File Type="POSTPLACE-PWROPT-DCP" Name="multi_8y_postplace_pwropt.dcp"/>
  <File Type="PHYSOPT-DCP" Name="multi_8y_physopt.dcp"/>
  <File Type="POSTROUTE-PHYSOPT-DCP" Name="multi_8y_postroute_physopt.dcp"/>
  <File Type="POSTROUTE-PHYSOPT-BLACKBOX-DCP" Name="multi_8y_postroute_physopt_bb.dcp"/>
  <File Type="ROUTE-METHODOLOGY-DRC-PB" Name="multi_8y_methodology_drc_routed.pb"/>
  <File Type="ROUTE-DRC-RPX" Name="multi_8y_drc_routed.rpx"/>
  <File Type="ROUTE-METHODOLOGY-DRC-RPX" Name="multi_8y_methodology_drc_routed.rpx"/>
  <File Type="PDI-FILE" Name="multi_8y.pdi"/>
  <File Type="RCFI_FILE" Name="multi_8y.rcfi"/>
  <File Type="CFI_FILE" Name="multi_8y.cfi"/>
  <File Type="RNPI_FILE" Name="multi_8y.rnpi"/>
  <File Type="NPI_FILE" Name="multi_8y.npi"/>
  <File Type="RBD_FILE" Name="multi_8y.rbd"/>
  <FileSet Name="sources" Type="DesignSrcs" RelSrcDir="$PSRCDIR/sources_1" RelGenDir="$PGENDIR/sources_1">
    <Filter Type="Srcs"/>
    <File Path="$PSRCDIR/sources_1/new/ALU8.v">
      <FileInfo>
        <Attr Name="ImportPath" Val="$PPRDIR/../lab_7_1_multi_8u/lab_7_1_multi_8u.srcs/sources_1/new/ALU8.v"/>
        <Attr Name="ImportTime" Val="1666147101"/>
        <Attr Name="UsedIn" Val="synthesis"/>
        <Attr Name="UsedIn" Val="implementation"/>
        <Attr Name="UsedIn" Val="simulation"/>
      </FileInfo>
    </File>
    <File Path="$PSRCDIR/sources_1/new/Adder8.v">
      <FileInfo>
        <Attr Name="ImportPath" Val="$PPRDIR/../lab_7_1_multi_8u/lab_7_1_multi_8u.srcs/sources_1/new/Adder8.v"/>
        <Attr Name="ImportTime" Val="1666144538"/>
        <Attr Name="UsedIn" Val="synthesis"/>
        <Attr Name="UsedIn" Val="implementation"/>
        <Attr Name="UsedIn" Val="simulation"/>
      </FileInfo>
    </File>
    <File Path="$PSRCDIR/sources_1/new/CLA4.v">
      <FileInfo>
        <Attr Name="ImportPath" Val="$PPRDIR/../lab_7_1_multi_8u/lab_7_1_multi_8u.srcs/sources_1/new/CLA4.v"/>
        <Attr Name="ImportTime" Val="1666144379"/>
        <Attr Name="UsedIn" Val="synthesis"/>
        <Attr Name="UsedIn" Val="implementation"/>
        <Attr Name="UsedIn" Val="simulation"/>
      </FileInfo>
    </File>
    <File Path="$PSRCDIR/sources_1/new/CLA8.v">
      <FileInfo>
        <Attr Name="ImportPath" Val="$PPRDIR/../lab_7_1_multi_8u/lab_7_1_multi_8u.srcs/sources_1/new/CLA8.v"/>
        <Attr Name="ImportTime" Val="1666144490"/>
        <Attr Name="UsedIn" Val="synthesis"/>
        <Attr Name="UsedIn" Val="implementation"/>
        <Attr Name="UsedIn" Val="simulation"/>
      </FileInfo>
    </File>
    <File Path="$PSRCDIR/sources_1/new/CLU4.v">
      <FileInfo>
        <Attr Name="ImportPath" Val="$PPRDIR/../lab_7_1_multi_8u/lab_7_1_multi_8u.srcs/sources_1/new/CLU4.v"/>
        <Attr Name="ImportTime" Val="1666144345"/>
        <Attr Name="UsedIn" Val="synthesis"/>
        <Attr Name="UsedIn" Val="implementation"/>
        <Attr Name="UsedIn" Val="simulation"/>
      </FileInfo>
    </File>
    <File Path="$PSRCDIR/sources_1/new/FA.v">
      <FileInfo>
        <Attr Name="ImportPath" Val="$PPRDIR/../lab_7_1_multi_8u/lab_7_1_multi_8u.srcs/sources_1/new/FA.v"/>
        <Attr Name="ImportTime" Val="1666144320"/>
        <Attr Name="UsedIn" Val="synthesis"/>
        <Attr Name="UsedIn" Val="implementation"/>
        <Attr Name="UsedIn" Val="simulation"/>
      </FileInfo>
    </File>
    <File Path="$PSRCDIR/sources_1/new/multi_8u.v">
      <FileInfo>
        <Attr Name="ImportPath" Val="$PPRDIR/../lab_7_1_multi_8u/lab_7_1_multi_8u.srcs/sources_1/new/multi_8u.v"/>
        <Attr Name="ImportTime" Val="1666150850"/>
        <Attr Name="UsedIn" Val="synthesis"/>
        <Attr Name="UsedIn" Val="implementation"/>
        <Attr Name="UsedIn" Val="simulation"/>
      </FileInfo>
    </File>
    <Config>
      <Option Name="DesignMode" Val="RTL"/>
      <Option Name="TopModule" Val="multi_8y"/>
      <Option Name="TopAutoSet" Val="TRUE"/>
    </Config>
  </FileSet>
  <FileSet Name="constrs_in" Type="Constrs" RelSrcDir="$PSRCDIR/constrs_1">
    <Filter Type="Constrs"/>
    <File Path="$PSRCDIR/constrs_1/new/multi_8u.xdc">
      <FileInfo>
        <Attr Name="ImportPath" Val="$PPRDIR/../lab_7_1_multi_8u/lab_7_1_multi_8u.srcs/constrs_1/new/multi_8u.xdc"/>
        <Attr Name="ImportTime" Val="1666149521"/>
        <Attr Name="UsedIn" Val="synthesis"/>
        <Attr Name="UsedIn" Val="implementation"/>
      </FileInfo>
    </File>
    <Config>
      <Option Name="ConstrsType" Val="XDC"/>
    </Config>
  </FileSet>
  <FileSet Name="utils" Type="Utils" RelSrcDir="$PSRCDIR/utils_1">
    <Filter Type="Utils"/>
    <Config>
      <Option Name="TopAutoSet" Val="TRUE"/>
    </Config>
  </FileSet>
  <Strategy Version="1" Minor="2">
    <StratHandle Name="Vivado Implementation Defaults" Flow="Vivado Implementation 2020"/>
    <Step Id="init_design"/>
    <Step Id="opt_design"/>
    <Step Id="power_opt_design"/>
    <Step Id="place_design"/>
    <Step Id="post_place_power_opt_design"/>
    <Step Id="phys_opt_design"/>
    <Step Id="route_design"/>
    <Step Id="post_route_phys_opt_design"/>
    <Step Id="write_bitstream"/>
    <Step Id="write_device_image"/>
  </Strategy>
</GenRun>
